gsecrets/__init__.py
gsecrets/__version__.py
gsecrets/cli.py
gsecrets/client.py
gsecrets/exceptions.py
gsecrets-1.3.3.dist-info/METADATA
gsecrets-1.3.3.dist-info/WHEEL
gsecrets-1.3.3.dist-info/entry_points.txt
gsecrets-1.3.3.dist-info/top_level.txt
gsecrets-1.3.3.dist-info/RECORD
