Metadata-Version: 2.1
Name: gsecrets
Version: 1.3.3
Summary: API and CLI for securely managing secrets
Home-page: https://github.com/openeemeter/gsecrets
Author: Recurve
Author-email: admin@recurve.com
License: Apache 2.0
Platform: UNKNOWN
Requires-Dist: click
Requires-Dist: google-api-python-client
Requires-Dist: google-cloud-storage
Requires-Dist: ndg-httpsclient
Requires-Dist: pyasn1 (==0.4.8)
Requires-Dist: pyopenssl (==19.1.0)
Requires-Dist: requests
